{"47726":{"model_id":"47726","model_make_id":"koenigsegg","model_name":"CC8S","model_trim":"","model_year":"2002","model_body":"Coupe","model_engine_position":"Middle","model_engine_cc":"4719","model_engine_cyl":"8","model_engine_type":"V","model_engine_valves_per_cyl":"4","model_engine_power_ps":"664","model_engine_power_rpm":"6500","model_engine_torque_nm":"752","model_engine_torque_rpm":"2000","model_engine_bore_mm":null,"model_engine_stroke_mm":null,"model_engine_compression":"8.6:1","model_engine_fuel":"Gasoline - Premium","model_top_speed_kph":"389","model_0_to_100_kph":"3.6","model_drive":"Rear","model_transmission_type":"Manual","model_seats":"2","model_doors":"2","model_weight_kg":"1175","model_length_mm":"4191","model_width_mm":"1989","model_height_mm":"1069","model_wheelbase_mm":"2659","model_lkm_hwy":null,"model_lkm_mixed":null,"model_lkm_city":null,"model_fuel_cap_l":null,"model_sold_in_us":"1","model_co2":null,"model_make_display":"Koenigsegg","make_display":"Koenigsegg","make_country":"Sweden"},"47727":{"model_id":"47727","model_make_id":"koenigsegg","model_name":"CC8S","model_trim":"","model_year":"2003","model_body":"Coupe","model_engine_position":"Middle","model_engine_cc":"4719","model_engine_cyl":"8","model_engine_type":"V","model_engine_valves_per_cyl":"4","model_engine_power_ps":"664","model_engine_power_rpm":"6500","model_engine_torque_nm":"752","model_engine_torque_rpm":"2000","model_engine_bore_mm":null,"model_engine_stroke_mm":null,"model_engine_compression":"8.6:1","model_engine_fuel":"Gasoline - Premium","model_top_speed_kph":"389","model_0_to_100_kph":"3.6","model_drive":"Rear","model_transmission_type":"Manual","model_seats":"2","model_doors":"2","model_weight_kg":"1175","model_length_mm":"4191","model_width_mm":"1989","model_height_mm":"1069","model_wheelbase_mm":"2659","model_lkm_hwy":null,"model_lkm_mixed":null,"model_lkm_city":null,"model_fuel_cap_l":null,"model_sold_in_us":"1","model_co2":null,"model_make_display":"Koenigsegg","make_display":"Koenigsegg","make_country":"Sweden"},"47728":{"model_id":"47728","model_make_id":"koenigsegg","model_name":"CC8S","model_trim":"","model_year":"2004","model_body":"Coupe","model_engine_position":"Middle","model_engine_cc":"4719","model_engine_cyl":"8","model_engine_type":"V","model_engine_valves_per_cyl":"4","model_engine_power_ps":"664","model_engine_power_rpm":"6500","model_engine_torque_nm":"752","model_engine_torque_rpm":"2000","model_engine_bore_mm":null,"model_engine_stroke_mm":null,"model_engine_compression":"8.6:1","model_engine_fuel":"Gasoline - Premium","model_top_speed_kph":"389","model_0_to_100_kph":"3.6","model_drive":"Rear","model_transmission_type":"Manual","model_seats":"2","model_doors":"2","model_weight_kg":"1175","model_length_mm":"4191","model_width_mm":"1989","model_height_mm":"1069","model_wheelbase_mm":"2659","model_lkm_hwy":null,"model_lkm_mixed":null,"model_lkm_city":null,"model_fuel_cap_l":null,"model_sold_in_us":"1","model_co2":null,"model_make_display":"Koenigsegg","make_display":"Koenigsegg","make_country":"Sweden"},"47729":{"model_id":"47729","model_make_id":"koenigsegg","model_name":"CC8S","model_trim":"","model_year":"2005","model_body":"Coupe","model_engine_position":"Middle","model_engine_cc":"4719","model_engine_cyl":"8","model_engine_type":"V","model_engine_valves_per_cyl":"4","model_engine_power_ps":"664","model_engine_power_rpm":"6500","model_engine_torque_nm":"752","model_engine_torque_rpm":"2000","model_engine_bore_mm":null,"model_engine_stroke_mm":null,"model_engine_compression":"8.6:1","model_engine_fuel":"Gasoline - Premium","model_top_speed_kph":"389","model_0_to_100_kph":"3.6","model_drive":"Rear","model_transmission_type":"Manual","model_seats":"2","model_doors":"2","model_weight_kg":"1175","model_length_mm":"4191","model_width_mm":"1989","model_height_mm":"1069","model_wheelbase_mm":"2659","model_lkm_hwy":null,"model_lkm_mixed":null,"model_lkm_city":null,"model_fuel_cap_l":null,"model_sold_in_us":"1","model_co2":null,"model_make_display":"Koenigsegg","make_display":"Koenigsegg","make_country":"Sweden"},"47730":{"model_id":"47730","model_make_id":"koenigsegg","model_name":"CCR","model_trim":"","model_year":"2005","model_body":"Coupe","model_engine_position":"Middle","model_engine_cc":"4719","model_engine_cyl":"8","model_engine_type":"V","model_engine_valves_per_cyl":"4","model_engine_power_ps":"827","model_engine_power_rpm":"6900","model_engine_torque_nm":"920","model_engine_torque_rpm":"5700","model_engine_bore_mm":null,"model_engine_stroke_mm":null,"model_engine_compression":"8.6:1","model_engine_fuel":"Gasoline - Premium","model_top_speed_kph":"394","model_0_to_100_kph":"3.2","model_drive":"Rear","model_transmission_type":"Manual","model_seats":"2","model_doors":"2","model_weight_kg":"1180","model_length_mm":"4191","model_width_mm":"1989","model_height_mm":"1069","model_wheelbase_mm":"2659","model_lkm_hwy":null,"model_lkm_mixed":null,"model_lkm_city":null,"model_fuel_cap_l":null,"model_sold_in_us":"1","model_co2":null,"model_make_display":"Koenigsegg","make_display":"Koenigsegg","make_country":"Sweden"},"47731":{"model_id":"47731","model_make_id":"koenigsegg","model_name":"CCR","model_trim":"","model_year":"2006","model_body":"Coupe","model_engine_position":"Middle","model_engine_cc":"4719","model_engine_cyl":"8","model_engine_type":"V","model_engine_valves_per_cyl":"4","model_engine_power_ps":"827","model_engine_power_rpm":"6900","model_engine_torque_nm":"920","model_engine_torque_rpm":"5700","model_engine_bore_mm":null,"model_engine_stroke_mm":null,"model_engine_compression":"8.6:1","model_engine_fuel":"Gasoline - Premium","model_top_speed_kph":"394","model_0_to_100_kph":"3.2","model_drive":"Rear","model_transmission_type":"Manual","model_seats":"2","model_doors":"2","model_weight_kg":"1180","model_length_mm":"4191","model_width_mm":"1989","model_height_mm":"1069","model_wheelbase_mm":"2659","model_lkm_hwy":null,"model_lkm_mixed":null,"model_lkm_city":null,"model_fuel_cap_l":null,"model_sold_in_us":"1","model_co2":null,"model_make_display":"Koenigsegg","make_display":"Koenigsegg","make_country":"Sweden"},"47732":{"model_id":"47732","model_make_id":"koenigsegg","model_name":"CCX","model_trim":"","model_year":"2006","model_body":"Roadster","model_engine_position":"Middle","model_engine_cc":"4719","model_engine_cyl":"8","model_engine_type":"V","model_engine_valves_per_cyl":"4","model_engine_power_ps":"817","model_engine_power_rpm":"6900","model_engine_torque_nm":"919","model_engine_torque_rpm":"5700","model_engine_bore_mm":null,"model_engine_stroke_mm":null,"model_engine_compression":"8.6:1","model_engine_fuel":"Gasoline","model_top_speed_kph":"400","model_0_to_100_kph":"3.2","model_drive":"Rear","model_transmission_type":"Manual","model_seats":"2","model_doors":"2","model_weight_kg":"1180","model_length_mm":"4293","model_width_mm":"1996","model_height_mm":"1120","model_wheelbase_mm":"2660","model_lkm_hwy":"17.0","model_lkm_mixed":"18.0","model_lkm_city":null,"model_fuel_cap_l":null,"model_sold_in_us":"1","model_co2":null,"model_make_display":"Koenigsegg","make_display":"Koenigsegg","make_country":"Sweden"},"47733":{"model_id":"47733","model_make_id":"koenigsegg","model_name":"CCX","model_trim":"","model_year":"2007","model_body":"Roadster","model_engine_position":"Middle","model_engine_cc":"4719","model_engine_cyl":"8","model_engine_type":"V","model_engine_valves_per_cyl":"4","model_engine_power_ps":"817","model_engine_power_rpm":"6900","model_engine_torque_nm":"919","model_engine_torque_rpm":"5700","model_engine_bore_mm":null,"model_engine_stroke_mm":null,"model_engine_compression":"8.6:1","model_engine_fuel":"Gasoline","model_top_speed_kph":"400","model_0_to_100_kph":"3.2","model_drive":"Rear","model_transmission_type":"Manual","model_seats":"2","model_doors":"2","model_weight_kg":"1180","model_length_mm":"4293","model_width_mm":"1996","model_height_mm":"1120","model_wheelbase_mm":"2660","model_lkm_hwy":"17.0","model_lkm_mixed":"18.0","model_lkm_city":null,"model_fuel_cap_l":null,"model_sold_in_us":"1","model_co2":null,"model_make_display":"Koenigsegg","make_display":"Koenigsegg","make_country":"Sweden"},"47734":{"model_id":"47734","model_make_id":"koenigsegg","model_name":"CCX","model_trim":"","model_year":"2008","model_body":"Roadster","model_engine_position":"Middle","model_engine_cc":"4719","model_engine_cyl":"8","model_engine_type":"V","model_engine_valves_per_cyl":"4","model_engine_power_ps":"817","model_engine_power_rpm":"6900","model_engine_torque_nm":"919","model_engine_torque_rpm":"5700","model_engine_bore_mm":null,"model_engine_stroke_mm":null,"model_engine_compression":"8.6:1","model_engine_fuel":"Gasoline","model_top_speed_kph":"400","model_0_to_100_kph":"3.2","model_drive":"Rear","model_transmission_type":"Manual","model_seats":"2","model_doors":"2","model_weight_kg":"1180","model_length_mm":"4293","model_width_mm":"1996","model_height_mm":"1120","model_wheelbase_mm":"2660","model_lkm_hwy":"17.0","model_lkm_mixed":"18.0","model_lkm_city":null,"model_fuel_cap_l":null,"model_sold_in_us":"1","model_co2":null,"model_make_display":"Koenigsegg","make_display":"Koenigsegg","make_country":"Sweden"},"47735":{"model_id":"47735","model_make_id":"koenigsegg","model_name":"CCX","model_trim":"","model_year":"2009","model_body":"Roadster","model_engine_position":"Middle","model_engine_cc":"4719","model_engine_cyl":"8","model_engine_type":"V","model_engine_valves_per_cyl":"4","model_engine_power_ps":"817","model_engine_power_rpm":"6900","model_engine_torque_nm":"919","model_engine_torque_rpm":"5700","model_engine_bore_mm":null,"model_engine_stroke_mm":null,"model_engine_compression":"8.6:1","model_engine_fuel":"Gasoline","model_top_speed_kph":"400","model_0_to_100_kph":"3.2","model_drive":"Rear","model_transmission_type":"Manual","model_seats":"2","model_doors":"2","model_weight_kg":"1180","model_length_mm":"4293","model_width_mm":"1996","model_height_mm":"1120","model_wheelbase_mm":"2660","model_lkm_hwy":"17.0","model_lkm_mixed":"18.0","model_lkm_city":null,"model_fuel_cap_l":null,"model_sold_in_us":"1","model_co2":null,"model_make_display":"Koenigsegg","make_display":"Koenigsegg","make_country":"Sweden"},"47736":{"model_id":"47736","model_make_id":"koenigsegg","model_name":"CCX","model_trim":"","model_year":"2010","model_body":"Roadster","model_engine_position":"Middle","model_engine_cc":"4719","model_engine_cyl":"8","model_engine_type":"V","model_engine_valves_per_cyl":"4","model_engine_power_ps":"817","model_engine_power_rpm":"6900","model_engine_torque_nm":"919","model_engine_torque_rpm":"5700","model_engine_bore_mm":null,"model_engine_stroke_mm":null,"model_engine_compression":"8.6:1","model_engine_fuel":"Gasoline","model_top_speed_kph":"400","model_0_to_100_kph":"3.2","model_drive":"Rear","model_transmission_type":"Manual","model_seats":"2","model_doors":"2","model_weight_kg":"1180","model_length_mm":"4293","model_width_mm":"1996","model_height_mm":"1120","model_wheelbase_mm":"2660","model_lkm_hwy":"17.0","model_lkm_mixed":"18.0","model_lkm_city":null,"model_fuel_cap_l":null,"model_sold_in_us":"1","model_co2":null,"model_make_display":"Koenigsegg","make_display":"Koenigsegg","make_country":"Sweden"},"47737":{"model_id":"47737","model_make_id":"koenigsegg","model_name":"CCX","model_trim":"","model_year":"2011","model_body":"Roadster","model_engine_position":"Middle","model_engine_cc":"4719","model_engine_cyl":"8","model_engine_type":"V","model_engine_valves_per_cyl":"4","model_engine_power_ps":"817","model_engine_power_rpm":"6900","model_engine_torque_nm":"919","model_engine_torque_rpm":"5700","model_engine_bore_mm":null,"model_engine_stroke_mm":null,"model_engine_compression":"8.6:1","model_engine_fuel":"Gasoline","model_top_speed_kph":"400","model_0_to_100_kph":"3.2","model_drive":"Rear","model_transmission_type":"Manual","model_seats":"2","model_doors":"2","model_weight_kg":"1180","model_length_mm":"4293","model_width_mm":"1996","model_height_mm":"1120","model_wheelbase_mm":"2660","model_lkm_hwy":"17.0","model_lkm_mixed":"18.0","model_lkm_city":null,"model_fuel_cap_l":null,"model_sold_in_us":"1","model_co2":null,"model_make_display":"Koenigsegg","make_display":"Koenigsegg","make_country":"Sweden"},"47738":{"model_id":"47738","model_make_id":"koenigsegg","model_name":"CCXR","model_trim":"","model_year":"2007","model_body":"Roadster","model_engine_position":"Middle","model_engine_cc":"4719","model_engine_cyl":"8","model_engine_type":"V","model_engine_valves_per_cyl":"4","model_engine_power_ps":"1079","model_engine_power_rpm":"7200","model_engine_torque_nm":"1060","model_engine_torque_rpm":"6100","model_engine_bore_mm":null,"model_engine_stroke_mm":null,"model_engine_compression":"8.8:1","model_engine_fuel":"Gasoline","model_top_speed_kph":"400","model_0_to_100_kph":"2.9","model_drive":"Rear","model_transmission_type":"Manual","model_seats":"2","model_doors":"2","model_weight_kg":"1280","model_length_mm":"4293","model_width_mm":"1996","model_height_mm":"1120","model_wheelbase_mm":"2660","model_lkm_hwy":"18.0","model_lkm_mixed":"22.0","model_lkm_city":null,"model_fuel_cap_l":null,"model_sold_in_us":"1","model_co2":null,"model_make_display":"Koenigsegg","make_display":"Koenigsegg","make_country":"Sweden"},"47739":{"model_id":"47739","model_make_id":"koenigsegg","model_name":"CCXR","model_trim":"","model_year":"2008","model_body":"Roadster","model_engine_position":"Middle","model_engine_cc":"4719","model_engine_cyl":"8","model_engine_type":"V","model_engine_valves_per_cyl":"4","model_engine_power_ps":"1079","model_engine_power_rpm":"7200","model_engine_torque_nm":"1060","model_engine_torque_rpm":"6100","model_engine_bore_mm":null,"model_engine_stroke_mm":null,"model_engine_compression":"8.8:1","model_engine_fuel":"Gasoline","model_top_speed_kph":"400","model_0_to_100_kph":"2.9","model_drive":"Rear","model_transmission_type":"Manual","model_seats":"2","model_doors":"2","model_weight_kg":"1280","model_length_mm":"4293","model_width_mm":"1996","model_height_mm":"1120","model_wheelbase_mm":"2660","model_lkm_hwy":"18.0","model_lkm_mixed":"22.0","model_lkm_city":null,"model_fuel_cap_l":null,"model_sold_in_us":"1","model_co2":null,"model_make_display":"Koenigsegg","make_display":"Koenigsegg","make_country":"Sweden"},"47740":{"model_id":"47740","model_make_id":"koenigsegg","model_name":"CCXR","model_trim":"","model_year":"2009","model_body":"Roadster","model_engine_position":"Middle","model_engine_cc":"4719","model_engine_cyl":"8","model_engine_type":"V","model_engine_valves_per_cyl":"4","model_engine_power_ps":"1079","model_engine_power_rpm":"7200","model_engine_torque_nm":"1060","model_engine_torque_rpm":"6100","model_engine_bore_mm":null,"model_engine_stroke_mm":null,"model_engine_compression":"8.8:1","model_engine_fuel":"Gasoline","model_top_speed_kph":"400","model_0_to_100_kph":"2.9","model_drive":"Rear","model_transmission_type":"Manual","model_seats":"2","model_doors":"2","model_weight_kg":"1280","model_length_mm":"4293","model_width_mm":"1996","model_height_mm":"1120","model_wheelbase_mm":"2660","model_lkm_hwy":"18.0","model_lkm_mixed":"22.0","model_lkm_city":null,"model_fuel_cap_l":null,"model_sold_in_us":"1","model_co2":null,"model_make_display":"Koenigsegg","make_display":"Koenigsegg","make_country":"Sweden"},"47741":{"model_id":"47741","model_make_id":"koenigsegg","model_name":"CCXR","model_trim":"","model_year":"2010","model_body":"Roadster","model_engine_position":"Middle","model_engine_cc":"4719","model_engine_cyl":"8","model_engine_type":"V","model_engine_valves_per_cyl":"4","model_engine_power_ps":"1079","model_engine_power_rpm":"7200","model_engine_torque_nm":"1060","model_engine_torque_rpm":"6100","model_engine_bore_mm":null,"model_engine_stroke_mm":null,"model_engine_compression":"8.8:1","model_engine_fuel":"Gasoline","model_top_speed_kph":"400","model_0_to_100_kph":"2.9","model_drive":"Rear","model_transmission_type":"Manual","model_seats":"2","model_doors":"2","model_weight_kg":"1280","model_length_mm":"4293","model_width_mm":"1996","model_height_mm":"1120","model_wheelbase_mm":"2660","model_lkm_hwy":"18.0","model_lkm_mixed":"22.0","model_lkm_city":null,"model_fuel_cap_l":null,"model_sold_in_us":"1","model_co2":null,"model_make_display":"Koenigsegg","make_display":"Koenigsegg","make_country":"Sweden"},"47742":{"model_id":"47742","model_make_id":"koenigsegg","model_name":"CCXR","model_trim":"","model_year":"2011","model_body":"Roadster","model_engine_position":"Middle","model_engine_cc":"4719","model_engine_cyl":"8","model_engine_type":"V","model_engine_valves_per_cyl":"4","model_engine_power_ps":"1079","model_engine_power_rpm":"7200","model_engine_torque_nm":"1060","model_engine_torque_rpm":"6100","model_engine_bore_mm":null,"model_engine_stroke_mm":null,"model_engine_compression":"8.8:1","model_engine_fuel":"Gasoline","model_top_speed_kph":"400","model_0_to_100_kph":"2.9","model_drive":"Rear","model_transmission_type":"Manual","model_seats":"2","model_doors":"2","model_weight_kg":"1280","model_length_mm":"4293","model_width_mm":"1996","model_height_mm":"1120","model_wheelbase_mm":"2660","model_lkm_hwy":"18.0","model_lkm_mixed":"22.0","model_lkm_city":null,"model_fuel_cap_l":null,"model_sold_in_us":"1","model_co2":null,"model_make_display":"Koenigsegg","make_display":"Koenigsegg","make_country":"Sweden"},"47743":{"model_id":"47743","model_make_id":"koenigsegg","model_name":"Agera","model_trim":"","model_year":"2011","model_body":"Coupe","model_engine_position":"Middle","model_engine_cc":"5000","model_engine_cyl":"8","model_engine_type":"V","model_engine_valves_per_cyl":"4","model_engine_power_ps":"940","model_engine_power_rpm":"6900","model_engine_torque_nm":"1100","model_engine_torque_rpm":"4000","model_engine_bore_mm":null,"model_engine_stroke_mm":null,"model_engine_compression":null,"model_engine_fuel":"Gasoline","model_top_speed_kph":null,"model_0_to_100_kph":null,"model_drive":"Rear","model_transmission_type":"Manual","model_seats":"2","model_doors":"2","model_weight_kg":"1290","model_length_mm":"4293","model_width_mm":"1996","model_height_mm":"1120","model_wheelbase_mm":"2660","model_lkm_hwy":null,"model_lkm_mixed":null,"model_lkm_city":null,"model_fuel_cap_l":null,"model_sold_in_us":"1","model_co2":null,"model_make_display":"Koenigsegg","make_display":"Koenigsegg","make_country":"Sweden"},"47744":{"model_id":"47744","model_make_id":"koenigsegg","model_name":"Agera","model_trim":"R","model_year":"2011","model_body":"Coupe","model_engine_position":"Middle","model_engine_cc":"5000","model_engine_cyl":"8","model_engine_type":"V","model_engine_valves_per_cyl":"4","model_engine_power_ps":"1115","model_engine_power_rpm":null,"model_engine_torque_nm":null,"model_engine_torque_rpm":null,"model_engine_bore_mm":null,"model_engine_stroke_mm":null,"model_engine_compression":null,"model_engine_fuel":"Biofuel","model_top_speed_kph":null,"model_0_to_100_kph":"2.9","model_drive":"Rear","model_transmission_type":"Manual","model_seats":"2","model_doors":"2","model_weight_kg":"1290","model_length_mm":"4293","model_width_mm":"1996","model_height_mm":"1120","model_wheelbase_mm":"2660","model_lkm_hwy":null,"model_lkm_mixed":null,"model_lkm_city":null,"model_fuel_cap_l":null,"model_sold_in_us":"1","model_co2":null,"model_make_display":"Koenigsegg","make_display":"Koenigsegg","make_country":"Sweden"},"51125":{"model_id":"51125","model_make_id":"koenigsegg","model_name":"Agera","model_trim":"R","model_year":"2012","model_body":"Coupe","model_engine_position":"Middle","model_engine_cc":"5000","model_engine_cyl":"8","model_engine_type":"V","model_engine_valves_per_cyl":"4","model_engine_power_ps":"1115","model_engine_power_rpm":null,"model_engine_torque_nm":null,"model_engine_torque_rpm":null,"model_engine_bore_mm":null,"model_engine_stroke_mm":null,"model_engine_compression":null,"model_engine_fuel":"Biofuel","model_top_speed_kph":null,"model_0_to_100_kph":"2.9","model_drive":"Rear","model_transmission_type":"Manual","model_seats":"2","model_doors":"2","model_weight_kg":"1290","model_length_mm":"4293","model_width_mm":"1996","model_height_mm":"1120","model_wheelbase_mm":"2660","model_lkm_hwy":null,"model_lkm_mixed":null,"model_lkm_city":null,"model_fuel_cap_l":null,"model_sold_in_us":"1","model_co2":null,"model_make_display":"Koenigsegg","make_display":"Koenigsegg","make_country":"Sweden"},"51126":{"model_id":"51126","model_make_id":"koenigsegg","model_name":"Agera","model_trim":"","model_year":"2012","model_body":"Coupe","model_engine_position":"Middle","model_engine_cc":"5000","model_engine_cyl":"8","model_engine_type":"V","model_engine_valves_per_cyl":"4","model_engine_power_ps":"940","model_engine_power_rpm":"6900","model_engine_torque_nm":"1100","model_engine_torque_rpm":"4000","model_engine_bore_mm":null,"model_engine_stroke_mm":null,"model_engine_compression":null,"model_engine_fuel":"Gasoline","model_top_speed_kph":null,"model_0_to_100_kph":null,"model_drive":"Rear","model_transmission_type":"Manual","model_seats":"2","model_doors":"2","model_weight_kg":"1290","model_length_mm":"4293","model_width_mm":"1996","model_height_mm":"1120","model_wheelbase_mm":"2660","model_lkm_hwy":null,"model_lkm_mixed":null,"model_lkm_city":null,"model_fuel_cap_l":null,"model_sold_in_us":"1","model_co2":null,"model_make_display":"Koenigsegg","make_display":"Koenigsegg","make_country":"Sweden"}}